Metadata-Version: 2.1
Name: parametrizer
Version: 0.0.1
Summary: Simple parametrizer class template
Home-page: https://github.com/davidemoro/parametrizer
Author: Davide Moro
Author-email: davide.moro@gmail.com
Maintainer: Davide Moro
Maintainer-email: davide.moro@gmail.com
License: Apache Software License 2.0
Platform: UNKNOWN
Classifier: Development Status :: 2 - Pre-Alpha
Classifier: Intended Audience :: Developers
Classifier: Programming Language :: Python
Classifier: Programming Language :: Python :: 2
Classifier: Programming Language :: Python :: 2.7
Classifier: Programming Language :: Python :: 3
Classifier: Programming Language :: Python :: 3.6
Classifier: Programming Language :: Python :: Implementation :: CPython
Classifier: Programming Language :: Python :: Implementation :: PyPy
Classifier: Operating System :: OS Independent
Classifier: License :: OSI Approved :: Apache Software License
Provides-Extra: tests
Provides-Extra: docs
